{
"type": "FeatureCollection",
"features": [
{ "type":"Feature","properties":{"osm_id":"5735211027","name":"Auto Partz Distribution","other":{"shop":"car_repair","service":"parts"}}, "geometry":{"type":"Point","coordinates":[-0.75485,51.63587 ]}},
{ "type":"Feature","properties":{"osm_id":"5949407914","name":"Abbey Distribution","other":{"website":"http:\/\/www.abbeydistribution.co.uk\/","industrial":"factory"}}, "geometry":{"type":"Point","coordinates":[-0.75507,51.63926 ]}}
]
}
